matplotlib-stubs/__init__.pyi
matplotlib-stubs/_afm.pyi
matplotlib-stubs/_api.pyi
matplotlib-stubs/_c_internal_utils.pyi
matplotlib-stubs/_cm.pyi
matplotlib-stubs/_color_data.pyi
matplotlib-stubs/_constrained_layout.pyi
matplotlib-stubs/_docstring.pyi
matplotlib-stubs/_enums.pyi
matplotlib-stubs/_fontconfig_pattern.pyi
matplotlib-stubs/_layoutgrid.pyi
matplotlib-stubs/_mathtext.pyi
matplotlib-stubs/_mathtext_data.pyi
matplotlib-stubs/_preprocess_data.pyi
matplotlib-stubs/_pylab_helpers.pyi
matplotlib-stubs/_text_helpers.pyi
matplotlib-stubs/_tight_bbox.pyi
matplotlib-stubs/_tight_layout.pyi
matplotlib-stubs/_version.pyi
matplotlib-stubs/afm.pyi
matplotlib-stubs/animation.pyi
matplotlib-stubs/artist.pyi
matplotlib-stubs/axis.pyi
matplotlib-stubs/backend_bases.pyi
matplotlib-stubs/backend_managers.pyi
matplotlib-stubs/backend_tools.pyi
matplotlib-stubs/bezier.pyi
matplotlib-stubs/blocking_input.pyi
matplotlib-stubs/category.pyi
matplotlib-stubs/cm.pyi
matplotlib-stubs/collections.pyi
matplotlib-stubs/colorbar.pyi
matplotlib-stubs/colorizer.pyi
matplotlib-stubs/colors.pyi
matplotlib-stubs/container.pyi
matplotlib-stubs/contour.pyi
matplotlib-stubs/dates.pyi
matplotlib-stubs/docstring.pyi
matplotlib-stubs/dviread.pyi
matplotlib-stubs/figure.pyi
matplotlib-stubs/font_manager.pyi
matplotlib-stubs/fontconfig_pattern.pyi
matplotlib-stubs/ft2font.pyi
matplotlib-stubs/gridspec.pyi
matplotlib-stubs/hatch.pyi
matplotlib-stubs/image.pyi
matplotlib-stubs/layout_engine.pyi
matplotlib-stubs/legend.pyi
matplotlib-stubs/legend_handler.pyi
matplotlib-stubs/lines.pyi
matplotlib-stubs/markers.pyi
matplotlib-stubs/mathtext.pyi
matplotlib-stubs/mlab.pyi
matplotlib-stubs/offsetbox.pyi
matplotlib-stubs/patches.pyi
matplotlib-stubs/path.pyi
matplotlib-stubs/patheffects.pyi
matplotlib-stubs/py.typed
matplotlib-stubs/pyplot.pyi
matplotlib-stubs/quiver.pyi
matplotlib-stubs/rcsetup.pyi
matplotlib-stubs/sankey.pyi
matplotlib-stubs/scale.pyi
matplotlib-stubs/spines.pyi
matplotlib_stubs-0.3.10.dist-info/METADATA
matplotlib_stubs-0.3.10.dist-info/WHEEL
matplotlib_stubs-0.3.10.dist-info/licenses/LICENSE
matplotlib_stubs-0.3.10.dist-info/RECORD
