Metadata-Version: 2.4
Name: matplotlib-stubs
Version: 0.3.10
Summary: Unofficial stubs for the matplotlib package.
Project-URL: Homepage, https://github.com/hoel-bagard/matplotlib-stubs
Project-URL: Bug Tracker, https://github.com/hoel-bagard/matplotlib-stubs/issues
Author: Bagard Hoel
License: MIT
License-File: LICENSE
Keywords: matplotlib,stubs
Classifier: Intended Audience :: Developers
Classifier: License :: OSI Approved :: MIT License
Classifier: Operating System :: OS Independent
Classifier: Programming Language :: Python
Classifier: Programming Language :: Python :: 3.8
Classifier: Programming Language :: Python :: 3.9
Classifier: Programming Language :: Python :: 3.10
Classifier: Programming Language :: Python :: 3.11
Classifier: Programming Language :: Python :: 3.12
Classifier: Programming Language :: Python :: 3.13
Classifier: Programming Language :: Python :: Implementation :: CPython
Requires-Python: >=3.8
Requires-Dist: matplotlib>=3.0
Requires-Dist: numpy>=1.21
Requires-Dist: pandas>=2.0
